README.md
setup.py
apache_beam_io_extras.egg-info/PKG-INFO
apache_beam_io_extras.egg-info/SOURCES.txt
apache_beam_io_extras.egg-info/dependency_links.txt
apache_beam_io_extras.egg-info/requires.txt
apache_beam_io_extras.egg-info/top_level.txt
beam_io_extras/__init__.py
beam_io_extras/elasticsearch.py
beam_io_extras/mongo.py
beam_io_extras/solr.py